{
  "items": [
    {
      "article": null,
      "author": {
        "avatar": "https://wpimg-wscn.awtmt.com/714916ad-9609-4245-94b4-dfe9518a63c3",
        "display_name": "万小婷",
        "id": 120000003969,
        "is_followed": false,
        "uri": "https://wallstreetcn.com/authors/120000003969"
      },
      "ban_comment": false,
      "channels": [
        "global-channel",
        "forex-channel",
        "a-stock-channel",
        "xgb-channel"
      ],
      "comment_count": 0,
      "content": "<p>商务部部长王文涛在京会见国际货币基金组织总裁格奥尔基耶娃，就全球和中国经济形势、加强多边合作等深入交换意见。王文涛强调，全球产业链供应链正日益受到政治、安全等非经济因素影响。一些国家搞“小院高墙”“脱钩断链”，滥用贸易保护措施，增加贸易往来成本，严重损害多边贸易体制和国际经贸秩序，导致全球经济碎片化。中国坚定支持自由贸易和真正的多边主义，期待与国际货币基金组织保持沟通，共同推动国际合作，为世界经济复苏发展贡献力量。（商务部网站）</p>\n",
      "content_more": "",
      "content_text": "商务部部长王文涛在京会见国际货币基金组织总裁格奥尔基耶娃，就全球和中国经济形势、加强多边合作等深入交换意见。王文涛强调，全球产业链供应链正日益受到政治、安全等非经济因素影响。一些国家搞“小院高墙”“脱钩断链”，滥用贸易保护措施，增加贸易往来成本，严重损害多边贸易体制和国际经贸秩序，导致全球经济碎片化。中国坚定支持自由贸易和真正的多边主义，期待与国际货币基金组织保持沟通，共同推动国际合作，为世界经济复苏发展贡献力量。（商务部网站）",
      "cover_images": [],
      "display_time": 1733753482,
      "fund_codes": [],
      "global_channel_name": "7x24快讯",
      "global_more_uri": "wscn://wallstreetcn.com/live",
      "has_live_reading": false,
      "highlight_title": "",
      "id": 2831389,
      "images": [],
      "is_calendar": false,
      "is_favourite": false,
      "is_priced": false,
      "is_scaling": false,
      "reference": "",
      "related_themes": [],
      "score": 1,
      "symbols": [],
      "tags": [],
      "title": "商务部部长王文涛会见国际货币基金组织总裁格奥尔基耶娃",
      "type": "live",
      "uri": "https://wallstreetcn.com/livenews/2831389"
    },
    {
      "article": null,
      "author": {
        "avatar": "https://wpimg-wscn.awtmt.com/714916ad-9609-4245-94b4-dfe9518a63c3",
        "display_name": "万小婷",
        "id": 120000003969,
        "is_followed": false,
        "uri": "https://wallstreetcn.com/authors/120000003969"
      },
      "ban_comment": false,
      "channels": [
        "global-channel",
        "forex-channel"
      ],
      "comment_count": 0,
      "content": "<p>据路透社报道，在美国当选总统特朗普呼吁俄乌立即停火并进行谈判以结束战争“疯狂（局面）”后，俄罗斯总统新闻秘书、克里姆林宫发言人佩斯科夫当地时间9日表示，克宫迄今为止没有接触特朗普或其团队。</p>\n",
      "content_more": "<p>报道称，当被问及是否与特朗普或其团队有过任何接触时，佩斯科夫说，“没有，仍然没有接触”。他表示，克宫已在周日罕见发表的声明中明确表明了其立场。（环球网）</p>\n",
      "content_text": "据路透社报道，在美国当选总统特朗普呼吁俄乌立即停火并进行谈判以结束战争“疯狂（局面）”后，俄罗斯总统新闻秘书、克里姆林宫发言人佩斯科夫当地时间9日表示，克宫迄今为止没有接触特朗普或其团队。",
      "cover_images": [],
      "display_time": 1733753348,
      "fund_codes": [],
      "global_channel_name": "7x24快讯",
      "global_more_uri": "wscn://wallstreetcn.com/live",
      "has_live_reading": false,
      "highlight_title": "",
      "id": 2831387,
      "images": [],
      "is_calendar": false,
      "is_favourite": false,
      "is_priced": false,
      "is_scaling": false,
      "reference": "",
      "related_themes": [],
      "score": 1,
      "symbols": [],
      "tags": [],
      "title": "特朗普呼吁俄乌立即停火并进行谈判后，克宫：迄今为止没有接触特朗普或其团队",
      "type": "live",
      "uri": "https://wallstreetcn.com/livenews/2831387"
    },
    {
      "article": null,
      "author": {
        "avatar": "https://wpimg-wscn.awtmt.com/714916ad-9609-4245-94b4-dfe9518a63c3",
        "display_name": "万小婷",
        "id": 120000003969,
        "is_followed": false,
        "uri": "https://wallstreetcn.com/authors/120000003969"
      },
      "ban_comment": false,
      "channels": [
        "global-channel"
      ],
      "comment_count": 0,
      "content": "<p>商务部部长王文涛在京会见经济合作与发展组织秘书长科尔曼，就世界经济形势、进一步深化双方合作等议题深入交换意见。王文涛表示，中国共产党二十届三中全会对进一步全面深化改革、推进中国式现代化作出系统部署，中国正加快构建新发展格局，以高质量发展全面推进中国式现代化，将为世界发展带来更多新机遇。中国正推动自主开放，持续在开放程度上做加法，在限制措施上做减法，开放的大门只会越开越大。</p>\n",
      "content_more": "<p>王文涛指出，中方愿在贸易投资、数字经济、绿色发展等领域同经合组织分享政策经验，开展人员交流，推进务实合作。希望经合组织能够继续发挥全球高标准国际规则“孵化器”的优势，同中方携手推动构建开放型世界经济，反对保护主义。（商务部网站）</p>\n",
      "content_text": "商务部部长王文涛在京会见经济合作与发展组织秘书长科尔曼，就世界经济形势、进一步深化双方合作等议题深入交换意见。王文涛表示，中国共产党二十届三中全会对进一步全面深化改革、推进中国式现代化作出系统部署，中国正加快构建新发展格局，以高质量发展全面推进中国式现代化，将为世界发展带来更多新机遇。中国正推动自主开放，持续在开放程度上做加法，在限制措施上做减法，开放的大门只会越开越大。",
      "cover_images": [],
      "display_time": 1733753209,
      "fund_codes": [],
      "global_channel_name": "7x24快讯",
      "global_more_uri": "wscn://wallstreetcn.com/live",
      "has_live_reading": false,
      "highlight_title": "",
      "id": 2831386,
      "images": [],
      "is_calendar": false,
      "is_favourite": false,
      "is_priced": false,
      "is_scaling": false,
      "reference": "",
      "related_themes": [],
      "score": 1,
      "symbols": [],
      "tags": [],
      "title": "商务部部长王文涛会见经合组织秘书长科尔曼",
      "type": "live",
      "uri": "https://wallstreetcn.com/livenews/2831386"
    },
    {
      "article": null,
      "author": {
        "avatar": "https://wpimg-wscn.awtmt.com/bc3971d4-2d62-4d54-b1dd-7058c60c6ffa",
        "display_name": "罗俊",
        "id": 694840,
        "is_followed": false,
        "uri": "https://wallstreetcn.com/authors/694840"
      },
      "ban_comment": false,
      "channels": [
        "global-channel",
        "us-stock-channel"
      ],
      "comment_count": 0,
      "content": "<p>据美国纽约联储数据，上个交易日（12月6日，非农日）担保隔夜融资利率（SOFR）报4.60%，之前一天报4.59%。</p>\n\n<p>上个交易日有效的联邦基金利率报4.58%，之前一天报4.58%。</p>\n",
      "content_more": "",
      "content_text": "据美国纽约联储数据，上个交易日（12月6日，非农日）担保隔夜融资利率（SOFR）报4.60%，之前一天报4.59%。\n\n上个交易日有效的联邦基金利率报4.58%，之前一天报4.58%。",
      "cover_images": [],
      "display_time": 1733753196,
      "fund_codes": [],
      "global_channel_name": "7x24快讯",
      "global_more_uri": "wscn://wallstreetcn.com/live",
      "has_live_reading": false,
      "highlight_title": "",
      "id": 2831385,
      "images": [],
      "is_calendar": false,
      "is_favourite": false,
      "is_priced": false,
      "is_scaling": false,
      "reference": "",
      "related_themes": [],
      "score": 1,
      "symbols": [],
      "tags": [],
      "title": "",
      "type": "live",
      "uri": "https://wallstreetcn.com/livenews/2831385"
    },
    {
      "article": null,
      "author": {
        "avatar": "https://wpimg-wscn.awtmt.com/bc3971d4-2d62-4d54-b1dd-7058c60c6ffa",
        "display_name": "罗俊",
        "id": 694840,
        "is_followed": false,
        "uri": "https://wallstreetcn.com/authors/694840"
      },
      "ban_comment": false,
      "channels": [
        "global-channel",
        "forex-channel"
      ],
      "comment_count": 0,
      "content": "<p>英国央行副行长Ramsden：政府预算报告发布以来，英国国债“的确出现非常有序的”重新定价。</p>\n",
      "content_more": "",
      "content_text": "英国央行副行长Ramsden：政府预算报告发布以来，英国国债“的确出现非常有序的”重新定价。",
      "cover_images": [],
      "display_time": 1733753124,
      "fund_codes": [],
      "global_channel_name": "7x24快讯",
      "global_more_uri": "wscn://wallstreetcn.com/live",
      "has_live_reading": false,
      "highlight_title": "",
      "id": 2831384,
      "images": [],
      "is_calendar": false,
      "is_favourite": false,
      "is_priced": false,
      "is_scaling": false,
      "reference": "",
      "related_themes": [],
      "score": 1,
      "symbols": [],
      "tags": [],
      "title": "",
      "type": "live",
      "uri": "https://wallstreetcn.com/livenews/2831384"
    },
    {
      "article": null,
      "author": {
        "avatar": "https://wpimg-wscn.awtmt.com/714916ad-9609-4245-94b4-dfe9518a63c3",
        "display_name": "万小婷",
        "id": 120000003969,
        "is_followed": false,
        "uri": "https://wallstreetcn.com/authors/120000003969"
      },
      "ban_comment": false,
      "channels": [
        "global-channel",
        "us-stock-channel",
        "hk-stock-channel"
      ],
      "comment_count": 0,
      "content": "<p>小米汽车第二款车正式登陆工信部。根据工信部信息，小米汽车第二款车型为纯电SUV，车辆尾标显示这款车型命名为“YU7”。新车长4999mm，宽1996mm，高1600mm，轴距达到3000mm，最高速度为253公里/小时。</p>\n",
      "content_more": "<p>当日晚间，小米科技董事长雷军在微博上回应称，小米YU7预计将在明年六七月正式上市。至于新车为什么这么早登陆工信部，雷军表示，这是因为小米希望YU7测试车可以尽早拆除重伪装，做更全面、更细致的长时间大规模测试，以确保产品质量。</p>\n\n<p>有业内人士分析，<strong>小米SU7对标特斯拉Model 3，预计小米第二款车YU7将对标特斯拉Model Y</strong>。（一财）</p>\n",
      "content_text": "小米汽车第二款车正式登陆工信部。根据工信部信息，小米汽车第二款车型为纯电SUV，车辆尾标显示这款车型命名为“YU7”。新车长4999mm，宽1996mm，高1600mm，轴距达到3000mm，最高速度为253公里/小时。",
      "cover_images": [],
      "display_time": 1733752983,
      "fund_codes": [],
      "global_channel_name": "7x24快讯",
      "global_more_uri": "wscn://wallstreetcn.com/live",
      "has_live_reading": false,
      "highlight_title": "",
      "id": 2831383,
      "images": [],
      "is_calendar": false,
      "is_favourite": false,
      "is_priced": false,
      "is_scaling": false,
      "reference": "",
      "related_themes": [],
      "score": 2,
      "symbols": [],
      "tags": [],
      "title": "年轻人的第一台“法拉利”？小米第二款车“YU7”登陆工信部公告",
      "type": "live",
      "uri": "https://wallstreetcn.com/livenews/2831383"
    },
    {
      "article": null,
      "author": {
        "avatar": "https://wpimg-wscn.awtmt.com/714916ad-9609-4245-94b4-dfe9518a63c3",
        "display_name": "万小婷",
        "id": 120000003969,
        "is_followed": false,
        "uri": "https://wallstreetcn.com/authors/120000003969"
      },
      "ban_comment": false,
      "channels": [
        "global-channel",
        "us-stock-channel",
        "hk-stock-channel",
        "forex-channel",
        "goldc-channel",
        "oil-channel"
      ],
      "comment_count": 0,
      "content": "<ul>\n<li><p>中共中央政治局召开会议，分析研究2025年经济工作，研究部署党风廉政建设和反腐败工作。</p></li>\n\n<li><p>加息埋伏笔？日央行罕见安排一月演讲及发布会。</p></li>\n\n<li><p>韩国法务部宣布禁止总统尹锡悦出境。</p></li>\n\n<li><p>据韩国经济日报，韩国主要反对党寻求周二通过预算及相关法案。</p></li>\n\n<li><p>据新华社，叙利亚反对派授权穆罕默德·巴希尔组建过渡政府。</p></li>\n\n<li><p>印度任命Sanjay Malhotra为印度央行行长，任期三年。</p></li>\n\n<li><p>英伟达涉嫌违反反垄断法，市场监管总局依法决定立案调查。</p></li>\n\n<li><p>小米YU7预计于明年6-7月正式上市。</p></li>\n\n<li><p>腾讯大股东Prosus继续减持：持股比例降至23.99%。</p></li>\n\n<li><p>MicroStrategy在12月2-8日以约21亿美元现金购买21,550枚比特币。</p></li>\n\n<li><p>美股盘前英伟达跌超2%，离岸人民币拉升，3倍做多富时中国ETF-Direxion涨逾18%，欧股上涨，韩国股汇双杀，现货黄金涨逾1%，现货白银涨3%。</p></li>\n\n<li><p>日经225指数收涨0.2%，沪指收跌0.05%，恒指收涨4.3%。</p></li>\n</ul>\n",
      "content_more": "",
      "content_text": "中共中央政治局召开会议，分析研究2025年经济工作，研究部署党风廉政建设和反腐败工作。\n\n加息埋伏笔？日央行罕见安排一月演讲及发布会。\n\n韩国法务部宣布禁止总统尹锡悦出境。\n\n据韩国经济日报，韩国主要反对党寻求周二通过预算及相关法案。\n\n据新华社，叙利亚反对派授权穆罕默德·巴希尔组建过渡政府。\n\n印度任命Sanjay Malhotra为印度央行行长，任期三年。\n\n英伟达涉嫌违反反垄断法，市场监管总局依法决定立案调查。\n\n小米YU7预计于明年6-7月正式上市。\n\n腾讯大股东Prosus继续减持：持股比例降至23.99%。\n\nMicroStrategy在12月2-8日以约21亿美元现金购买21,550枚比特币。\n\n美股盘前英伟达跌超2%，离岸人民币拉升，3倍做多富时中国ETF-Direxion涨逾18%，欧股上涨，韩国股汇双杀，现货黄金涨逾1%，现货白银涨3%。\n\n日经225指数收涨0.2%，沪指收跌0.05%，恒指收涨4.3%。",
      "cover_images": [],
      "display_time": 1733752858,
      "fund_codes": [],
      "global_channel_name": "7x24快讯",
      "global_more_uri": "wscn://wallstreetcn.com/live",
      "has_live_reading": false,
      "highlight_title": "",
      "id": 2831388,
      "images": [],
      "is_calendar": false,
      "is_favourite": false,
      "is_priced": false,
      "is_scaling": false,
      "reference": "",
      "related_themes": [],
      "score": 3,
      "symbols": [],
      "tags": [],
      "title": "周一美股盘前你需要了解的全球要闻",
      "type": "live",
      "uri": "https://wallstreetcn.com/livenews/2831388"
    },
    {
      "article": null,
      "author": {
        "avatar": "https://wpimg-wscn.awtmt.com/ivanka_avatar_7.png",
        "display_name": "葛冬瑾",
        "id": 120000004519,
        "is_followed": false,
        "uri": "https://wallstreetcn.com/authors/120000004519"
      },
      "ban_comment": false,
      "channels": [
        "global-channel"
      ],
      "comment_count": 0,
      "content": "<p>包钢集团与华为技术有限公司签署战略合作协议。双方本次战略合作协议的签署，将在数字化人才培养、智慧矿山、数据治理、皮带智能化、稀土数字化、稀土供应等领域展开合作，共同推动企业数字化转型与双方的创新发展。（证券时报）</p>\n",
      "content_more": "",
      "content_text": "包钢集团与华为技术有限公司签署战略合作协议。双方本次战略合作协议的签署，将在数字化人才培养、智慧矿山、数据治理、皮带智能化、稀土数字化、稀土供应等领域展开合作，共同推动企业数字化转型与双方的创新发展。（证券时报）",
      "cover_images": [],
      "display_time": 1733752757,
      "fund_codes": [],
      "global_channel_name": "7x24快讯",
      "global_more_uri": "wscn://wallstreetcn.com/live",
      "has_live_reading": false,
      "highlight_title": "",
      "id": 2831382,
      "images": [],
      "is_calendar": false,
      "is_favourite": false,
      "is_priced": false,
      "is_scaling": false,
      "reference": "",
      "related_themes": [],
      "score": 1,
      "symbols": [],
      "tags": [],
      "title": "包钢集团与华为签署战略合作协议 将在稀土数字化、稀土供应等领域合作",
      "type": "live",
      "uri": "https://wallstreetcn.com/livenews/2831382"
    },
    {
      "article": null,
      "author": {
        "avatar": "https://wpimg-wscn.awtmt.com/ivanka_avatar_7.png",
        "display_name": "葛冬瑾",
        "id": 120000004519,
        "is_followed": false,
        "uri": "https://wallstreetcn.com/authors/120000004519"
      },
      "ban_comment": false,
      "channels": [
        "global-channel",
        "goldc-channel",
        "financing-channel"
      ],
      "comment_count": 0,
      "content": "<p>数据显示，截至11月底，A股上市交易的14只商品类黄金ETF年内均获资金净买入。4月至11月，其中两只ETF持续8个月获得资金净流入，上海金ETF（518600）为其中净买入最多的一只，区间净流入额达3.7亿元，资金关注度颇高。（中证网）</p>\n",
      "content_more": "",
      "content_text": "数据显示，截至11月底，A股上市交易的14只商品类黄金ETF年内均获资金净买入。4月至11月，其中两只ETF持续8个月获得资金净流入，上海金ETF（518600）为其中净买入最多的一只，区间净流入额达3.7亿元，资金关注度颇高。（中证网）",
      "cover_images": [],
      "display_time": 1733752491,
      "fund_codes": [],
      "global_channel_name": "7x24快讯",
      "global_more_uri": "wscn://wallstreetcn.com/live",
      "has_live_reading": false,
      "highlight_title": "",
      "id": 2831381,
      "images": [],
      "is_calendar": false,
      "is_favourite": false,
      "is_priced": false,
      "is_scaling": false,
      "reference": "",
      "related_themes": [],
      "score": 1,
      "symbols": [],
      "tags": [],
      "title": "央行增持黄金释放积极信号 上海金ETF连续8个月获资金净买入",
      "type": "live",
      "uri": "https://wallstreetcn.com/livenews/2831381"
    },
    {
      "article": null,
      "author": {
        "avatar": "https://wpimg-wscn.awtmt.com/714916ad-9609-4245-94b4-dfe9518a63c3",
        "display_name": "万小婷",
        "id": 120000003969,
        "is_followed": false,
        "uri": "https://wallstreetcn.com/authors/120000003969"
      },
      "ban_comment": false,
      "channels": [
        "global-channel",
        "forex-channel"
      ],
      "comment_count": 0,
      "content": "<p>英国央行副行长Ramsden（就货币紧缩发表评论）：我们采取的方法经受住了时间的考验。</p>\n",
      "content_more": "",
      "content_text": "英国央行副行长Ramsden（就货币紧缩发表评论）：我们采取的方法经受住了时间的考验。",
      "cover_images": [],
      "display_time": 1733752080,
      "fund_codes": [],
      "global_channel_name": "7x24快讯",
      "global_more_uri": "wscn://wallstreetcn.com/live",
      "has_live_reading": false,
      "highlight_title": "",
      "id": 2831379,
      "images": [],
      "is_calendar": false,
      "is_favourite": false,
      "is_priced": false,
      "is_scaling": false,
      "reference": "",
      "related_themes": [],
      "score": 1,
      "symbols": [],
      "tags": [],
      "title": "",
      "type": "live",
      "uri": "https://wallstreetcn.com/livenews/2831379"
    },
    {
      "article": null,
      "author": {
        "avatar": "https://wpimg-wscn.awtmt.com/ivanka_avatar_7.png",
        "display_name": "葛冬瑾",
        "id": 120000004519,
        "is_followed": false,
        "uri": "https://wallstreetcn.com/authors/120000004519"
      },
      "ban_comment": false,
      "channels": [
        "global-channel",
        "us-stock-channel"
      ],
      "comment_count": 0,
      "content": "<p>华尔街见闻获悉，口服版司美格鲁肽于12月9日晚21点在美团启动全网首发预售。同时间，还有被行业公认为司美格鲁肽的“最强对手”的替尔泊肽在美团开启首发预约，部分地区用户可预约到同城门诊进行体重管理，有消息称一周内还将开放预定送药到家服务。这也是继诺和盈（司美减重版）后，美团再度拿下两款明星药的首发预约。美团数据显示，司美相关产品的瞬时搜索量环比昨日翻倍。（全天候科技）</p>\n",
      "content_more": "",
      "content_text": "华尔街见闻获悉，口服版司美格鲁肽于12月9日晚21点在美团启动全网首发预售。同时间，还有被行业公认为司美格鲁肽的“最强对手”的替尔泊肽在美团开启首发预约，部分地区用户可预约到同城门诊进行体重管理，有消息称一周内还将开放预定送药到家服务。这也是继诺和盈（司美减重版）后，美团再度拿下两款明星药的首发预约。美团数据显示，司美相关产品的瞬时搜索量环比昨日翻倍。（全天候科技）",
      "cover_images": [],
      "display_time": 1733751632,
      "fund_codes": [],
      "global_channel_name": "7x24快讯",
      "global_more_uri": "wscn://wallstreetcn.com/live",
      "has_live_reading": false,
      "highlight_title": "",
      "id": 2831378,
      "images": [],
      "is_calendar": false,
      "is_favourite": false,
      "is_priced": false,
      "is_scaling": false,
      "reference": "",
      "related_themes": [],
      "score": 2,
      "symbols": [],
      "tags": [],
      "title": "中国首个口服版本司美格鲁肽美团首发预售",
      "type": "live",
      "uri": "https://wallstreetcn.com/livenews/2831378"
    },
    {
      "article": null,
      "author": {
        "avatar": "https://wpimg-wscn.awtmt.com/714916ad-9609-4245-94b4-dfe9518a63c3",
        "display_name": "万小婷",
        "id": 120000003969,
        "is_followed": false,
        "uri": "https://wallstreetcn.com/authors/120000003969"
      },
      "ban_comment": false,
      "channels": [
        "global-channel",
        "goldc-channel"
      ],
      "comment_count": 0,
      "content": "<p>现货白银日内涨幅达3%，报31.91美元/盎司。</p>\n",
      "content_more": "",
      "content_text": "现货白银日内涨幅达3%，报31.91美元/盎司。",
      "cover_images": [],
      "display_time": 1733751603,
      "fund_codes": [],
      "global_channel_name": "7x24快讯",
      "global_more_uri": "wscn://wallstreetcn.com/live",
      "has_live_reading": false,
      "highlight_title": "",
      "id": 2831377,
      "images": [],
      "is_calendar": false,
      "is_favourite": false,
      "is_priced": false,
      "is_scaling": false,
      "reference": "",
      "related_themes": [],
      "score": 2,
      "symbols": [],
      "tags": [],
      "title": "",
      "type": "live",
      "uri": "https://wallstreetcn.com/livenews/2831377"
    },
    {
      "article": null,
      "author": {
        "avatar": "https://wpimg-wscn.awtmt.com/ivanka_avatar_7.png",
        "display_name": "葛冬瑾",
        "id": 120000004519,
        "is_followed": false,
        "uri": "https://wallstreetcn.com/authors/120000004519"
      },
      "ban_comment": false,
      "channels": [
        "global-channel",
        "forex-channel"
      ],
      "comment_count": 0,
      "content": "<p>据商务部网站，商务部部长王文涛在京会见世贸组织总干事伊维拉，双方就世贸组织改革、深化中国与世贸组织合作等深入交换意见。</p>\n\n<p>王文涛表示，世贸组织改革对于应对全球共同挑战具有重要意义，中方愿与各方共同努力，推动改革取得积极进展。中方支持世贸组织在发展领域取得更多成果，呼吁恢复争端解决机制正常运转。中方支持尽早将投资便利化协定纳入世贸组织法律框架，达成渔业补贴第二阶段协议，结束电子商务联合声明倡议谈判，推动多边贸易规则与时俱进。</p>\n",
      "content_more": "",
      "content_text": "据商务部网站，商务部部长王文涛在京会见世贸组织总干事伊维拉，双方就世贸组织改革、深化中国与世贸组织合作等深入交换意见。\n\n王文涛表示，世贸组织改革对于应对全球共同挑战具有重要意义，中方愿与各方共同努力，推动改革取得积极进展。中方支持世贸组织在发展领域取得更多成果，呼吁恢复争端解决机制正常运转。中方支持尽早将投资便利化协定纳入世贸组织法律框架，达成渔业补贴第二阶段协议，结束电子商务联合声明倡议谈判，推动多边贸易规则与时俱进。",
      "cover_images": [],
      "display_time": 1733751333,
      "fund_codes": [],
      "global_channel_name": "7x24快讯",
      "global_more_uri": "wscn://wallstreetcn.com/live",
      "has_live_reading": false,
      "highlight_title": "",
      "id": 2831376,
      "images": [],
      "is_calendar": false,
      "is_favourite": false,
      "is_priced": false,
      "is_scaling": false,
      "reference": "",
      "related_themes": [],
      "score": 1,
      "symbols": [],
      "tags": [],
      "title": "商务部部长王文涛部长会见世贸组织总干事伊维拉",
      "type": "live",
      "uri": "https://wallstreetcn.com/livenews/2831376"
    },
    {
      "article": null,
      "author": {
        "avatar": "https://wpimg-wscn.awtmt.com/714916ad-9609-4245-94b4-dfe9518a63c3",
        "display_name": "万小婷",
        "id": 120000003969,
        "is_followed": false,
        "uri": "https://wallstreetcn.com/authors/120000003969"
      },
      "ban_comment": false,
      "channels": [
        "global-channel",
        "goldc-channel"
      ],
      "comment_count": 0,
      "content": "<p>纽约银日内涨幅达3%，报32.54美元/盎司。</p>\n",
      "content_more": "",
      "content_text": "纽约银日内涨幅达3%，报32.54美元/盎司。",
      "cover_images": [],
      "display_time": 1733751263,
      "fund_codes": [],
      "global_channel_name": "7x24快讯",
      "global_more_uri": "wscn://wallstreetcn.com/live",
      "has_live_reading": false,
      "highlight_title": "",
      "id": 2831375,
      "images": [],
      "is_calendar": false,
      "is_favourite": false,
      "is_priced": false,
      "is_scaling": false,
      "reference": "",
      "related_themes": [],
      "score": 2,
      "symbols": [],
      "tags": [],
      "title": "",
      "type": "live",
      "uri": "https://wallstreetcn.com/livenews/2831375"
    },
    {
      "article": null,
      "author": {
        "avatar": "https://wpimg-wscn.awtmt.com/714916ad-9609-4245-94b4-dfe9518a63c3",
        "display_name": "万小婷",
        "id": 120000003969,
        "is_followed": false,
        "uri": "https://wallstreetcn.com/authors/120000003969"
      },
      "ban_comment": false,
      "channels": [
        "global-channel",
        "forex-channel"
      ],
      "comment_count": 0,
      "content": "<p>澳元兑美元上涨1%，至0.6459的盘中高点。</p>\n",
      "content_more": "",
      "content_text": "澳元兑美元上涨1%，至0.6459的盘中高点。",
      "cover_images": [],
      "display_time": 1733750540,
      "fund_codes": [],
      "global_channel_name": "7x24快讯",
      "global_more_uri": "wscn://wallstreetcn.com/live",
      "has_live_reading": false,
      "highlight_title": "",
      "id": 2831373,
      "images": [],
      "is_calendar": false,
      "is_favourite": false,
      "is_priced": false,
      "is_scaling": false,
      "reference": "",
      "related_themes": [],
      "score": 2,
      "symbols": [],
      "tags": [],
      "title": "",
      "type": "live",
      "uri": "https://wallstreetcn.com/livenews/2831373"
    },
    {
      "article": null,
      "author": {
        "avatar": "https://wpimg-wscn.awtmt.com/ivanka_avatar_7.png",
        "display_name": "葛冬瑾",
        "id": 120000004519,
        "is_followed": false,
        "uri": "https://wallstreetcn.com/authors/120000004519"
      },
      "ban_comment": false,
      "channels": [
        "global-channel",
        "a-stock-channel",
        "xgb-channel"
      ],
      "comment_count": 0,
      "content": "<p>据上观新闻，上海市长龚正今天（12月9日）主持召开市政府常务会议，要求按照市委部署，推进今年市政府总体目标高质量完成；率先探索超大城市新型城镇化道路；提升上海航空物流枢纽能级；提升上海历史风貌保护管理水平。</p>\n",
      "content_more": "<p>会议原则同意《关于进一步提升上海航空物流枢纽能级的若干措施》并指出，打造全方位门户复合型国际航空枢纽，要建强“硬设施”，加快建设完善浦东、虹桥航空货运枢纽和配套交通集疏运体系，特别是加快推进适应跨境电商发展的基础设施建设。要优化“软服务”，机场、口岸、空管等单位要紧密协同，加大协作力度，提升机场物流整体效率。要营造“生态圈”，保障航空货运供应链稳定、安全、自主可控，吸引多元经营主体主动参与、共建共享。</p>\n",
      "content_text": "据上观新闻，上海市长龚正今天（12月9日）主持召开市政府常务会议，要求按照市委部署，推进今年市政府总体目标高质量完成；率先探索超大城市新型城镇化道路；提升上海航空物流枢纽能级；提升上海历史风貌保护管理水平。",
      "cover_images": [],
      "display_time": 1733750460,
      "fund_codes": [],
      "global_channel_name": "7x24快讯",
      "global_more_uri": "wscn://wallstreetcn.com/live",
      "has_live_reading": false,
      "highlight_title": "",
      "id": 2831372,
      "images": [],
      "is_calendar": false,
      "is_favourite": false,
      "is_priced": false,
      "is_scaling": false,
      "reference": "",
      "related_themes": [],
      "score": 1,
      "symbols": [],
      "tags": [],
      "title": "上海市政府常务会部署，提升上海航空物流枢纽能级",
      "type": "live",
      "uri": "https://wallstreetcn.com/livenews/2831372"
    },
    {
      "article": null,
      "author": {
        "avatar": "https://wpimg-wscn.awtmt.com/ivanka_avatar_7.png",
        "display_name": "葛冬瑾",
        "id": 120000004519,
        "is_followed": false,
        "uri": "https://wallstreetcn.com/authors/120000004519"
      },
      "ban_comment": false,
      "channels": [
        "global-channel",
        "forex-channel"
      ],
      "comment_count": 0,
      "content": "<p>据亲叙利亚反对派媒体12月9日报道，反对派授权“叙利亚救国政府”的穆罕默德·巴希尔组建叙利亚过渡政府。“叙利亚救国政府”由叙反对派成立，巴希尔担任其总理。（新华社）</p>\n",
      "content_more": "",
      "content_text": "据亲叙利亚反对派媒体12月9日报道，反对派授权“叙利亚救国政府”的穆罕默德·巴希尔组建叙利亚过渡政府。“叙利亚救国政府”由叙反对派成立，巴希尔担任其总理。（新华社）",
      "cover_images": [],
      "display_time": 1733750159,
      "fund_codes": [],
      "global_channel_name": "7x24快讯",
      "global_more_uri": "wscn://wallstreetcn.com/live",
      "has_live_reading": false,
      "highlight_title": "",
      "id": 2831371,
      "images": [],
      "is_calendar": false,
      "is_favourite": false,
      "is_priced": false,
      "is_scaling": false,
      "reference": "",
      "related_themes": [],
      "score": 2,
      "symbols": [],
      "tags": [],
      "title": "叙利亚反对派授权穆罕默德·巴希尔组建过渡政府",
      "type": "live",
      "uri": "https://wallstreetcn.com/livenews/2831371"
    },
    {
      "article": null,
      "author": {
        "avatar": "https://wpimg-wscn.awtmt.com/ivanka_avatar_7.png",
        "display_name": "葛冬瑾",
        "id": 120000004519,
        "is_followed": false,
        "uri": "https://wallstreetcn.com/authors/120000004519"
      },
      "ban_comment": false,
      "channels": [
        "global-channel",
        "bond-channel"
      ],
      "comment_count": 0,
      "content": "<p>据新华社，中共中央政治局12月9日召开会议，分析研究2025年经济工作。东方金诚判断，2025年央行会继续实施有力度的降息降准，其中政策性降息幅度有可能达到0.5个百分点，明显高于今年0.3个百分点的降息幅度，而且各类结构性货币政策工具利率也会适时下调，进而引导企业和居民融资成本下行。不排除2025年通过较大幅度引导5年期以上LPR报价下行等方式，继续对居民房贷实施较大力度定向降息的可能。（澎湃新闻）</p>\n",
      "content_more": "",
      "content_text": "据新华社，中共中央政治局12月9日召开会议，分析研究2025年经济工作。东方金诚判断，2025年央行会继续实施有力度的降息降准，其中政策性降息幅度有可能达到0.5个百分点，明显高于今年0.3个百分点的降息幅度，而且各类结构性货币政策工具利率也会适时下调，进而引导企业和居民融资成本下行。不排除2025年通过较大幅度引导5年期以上LPR报价下行等方式，继续对居民房贷实施较大力度定向降息的可能。（澎湃新闻）",
      "cover_images": [],
      "display_time": 1733750060,
      "fund_codes": [],
      "global_channel_name": "7x24快讯",
      "global_more_uri": "wscn://wallstreetcn.com/live",
      "has_live_reading": false,
      "highlight_title": "",
      "id": 2831370,
      "images": [],
      "is_calendar": false,
      "is_favourite": false,
      "is_priced": false,
      "is_scaling": false,
      "reference": "",
      "related_themes": [],
      "score": 1,
      "symbols": [],
      "tags": [],
      "title": "东方金诚：2025年政策性降息幅度有可能达到0.5个百分点",
      "type": "live",
      "uri": "https://wallstreetcn.com/livenews/2831370"
    },
    {
      "article": null,
      "author": {
        "avatar": "https://wpimg-wscn.awtmt.com/714916ad-9609-4245-94b4-dfe9518a63c3",
        "display_name": "万小婷",
        "id": 120000003969,
        "is_followed": false,
        "uri": "https://wallstreetcn.com/authors/120000003969"
      },
      "ban_comment": false,
      "channels": [
        "global-channel",
        "commodity-channel"
      ],
      "comment_count": 0,
      "content": "<p>“比特币持仓大户”MicroStrategy在12月2-8日以约21亿美元现金购买21,550枚比特币。MicroStrategy在12月2-8日以21.3亿美元的价格卖出了542万股股份。</p>\n",
      "content_more": "",
      "content_text": "“比特币持仓大户”MicroStrategy在12月2-8日以约21亿美元现金购买21,550枚比特币。MicroStrategy在12月2-8日以21.3亿美元的价格卖出了542万股股份。",
      "cover_images": [],
      "display_time": 1733749542,
      "fund_codes": [],
      "global_channel_name": "7x24快讯",
      "global_more_uri": "wscn://wallstreetcn.com/live",
      "has_live_reading": false,
      "highlight_title": "",
      "id": 2831369,
      "images": [],
      "is_calendar": false,
      "is_favourite": false,
      "is_priced": false,
      "is_scaling": false,
      "reference": "",
      "related_themes": [],
      "score": 2,
      "symbols": [],
      "tags": [],
      "title": "MicroStrategy在12月2-8日购买21,550枚比特币",
      "type": "live",
      "uri": "https://wallstreetcn.com/livenews/2831369"
    },
    {
      "article": null,
      "author": {
        "avatar": "https://wpimg-wscn.awtmt.com/714916ad-9609-4245-94b4-dfe9518a63c3",
        "display_name": "万小婷",
        "id": 120000003969,
        "is_followed": false,
        "uri": "https://wallstreetcn.com/authors/120000003969"
      },
      "ban_comment": false,
      "channels": [
        "global-channel"
      ],
      "comment_count": 0,
      "content": "<p>波罗的海干散货指数涨0.09%，至1168点。</p>\n",
      "content_more": "",
      "content_text": "波罗的海干散货指数涨0.09%，至1168点。",
      "cover_images": [],
      "display_time": 1733749346,
      "fund_codes": [],
      "global_channel_name": "7x24快讯",
      "global_more_uri": "wscn://wallstreetcn.com/live",
      "has_live_reading": false,
      "highlight_title": "",
      "id": 2831367,
      "images": [],
      "is_calendar": false,
      "is_favourite": false,
      "is_priced": false,
      "is_scaling": false,
      "reference": "",
      "related_themes": [],
      "score": 1,
      "symbols": [],
      "tags": [],
      "title": "",
      "type": "live",
      "uri": "https://wallstreetcn.com/livenews/2831367"
    }
  ],
  "next_cursor": "1733749346",
  "op_cursor": "11114354",
  "polling_cursor": "2831389"
}
